asutils/__init__.py
asutils/cli.py
asutils/git.py
asutils/publish.py
asutils/repo.py
asutils/claude/__init__.py
asutils/claude/cli.py
asutils/claude/skill.py
asutils/claude/agents/__init__.py
asutils/claude/agents/cli.py
asutils/claude/agents/definitions/code-review.yaml
asutils/claude/permissions/__init__.py
asutils/claude/permissions/cli.py
asutils/claude/permissions/hook.py
asutils/claude/permissions/profiles/default.yaml
asutils/claude/permissions/profiles/dev.yaml
asutils/claude/permissions/profiles/readonly.yaml
asutils/claude/permissions/profiles/yolo.yaml
asutils/claude/skills/claude-hooks.md
asutils/claude/tts/__init__.py
asutils/claude/tts/cli.py
asutils/claude/tts/hook.py
asutils/claude/tts/session_hook.py
asutils/claude/tts/speak.py
asutils/claude/tts/commands/tts.md
asutils/envsetup/__init__.py
asutils/envsetup/cli.py
asutils/utils/__init__.py
asutils/utils/treeview.py
asutils-0.2.18.dist-info/METADATA
asutils-0.2.18.dist-info/WHEEL
asutils-0.2.18.dist-info/entry_points.txt
asutils-0.2.18.dist-info/licenses/LICENSE
asutils-0.2.18.dist-info/RECORD
